db_connections/CHANGELOG.md
db_connections/LICENSE
db_connections/README.md
db_connections/__init__.py
db_connections/scr/all_db_connectors/__init__.py
db_connections/scr/all_db_connectors/connectors/__init__.py
db_connections/scr/all_db_connectors/connectors/clickhouse/Setup_guide.md
db_connections/scr/all_db_connectors/connectors/clickhouse/__init__.py
db_connections/scr/all_db_connectors/connectors/clickhouse/clickhouse_usage.py
db_connections/scr/all_db_connectors/connectors/clickhouse/config.py
db_connections/scr/all_db_connectors/connectors/clickhouse/exceptions.py
db_connections/scr/all_db_connectors/connectors/clickhouse/health.py
db_connections/scr/all_db_connectors/connectors/clickhouse/pool.py
db_connections/scr/all_db_connectors/connectors/mongodb/Setup_guide.md
db_connections/scr/all_db_connectors/connectors/mongodb/__init__.py
db_connections/scr/all_db_connectors/connectors/mongodb/config.py
db_connections/scr/all_db_connectors/connectors/mongodb/exceptions.py
db_connections/scr/all_db_connectors/connectors/mongodb/health.py
db_connections/scr/all_db_connectors/connectors/mongodb/mongodb_usage.py
db_connections/scr/all_db_connectors/connectors/mongodb/pool.py
db_connections/scr/all_db_connectors/connectors/neo4j/Setup_guide.md
db_connections/scr/all_db_connectors/connectors/neo4j/__init__.py
db_connections/scr/all_db_connectors/connectors/neo4j/config.py
db_connections/scr/all_db_connectors/connectors/neo4j/exceptions.py
db_connections/scr/all_db_connectors/connectors/neo4j/health.py
db_connections/scr/all_db_connectors/connectors/neo4j/neo4j_usage.py
db_connections/scr/all_db_connectors/connectors/neo4j/pool.py
db_connections/scr/all_db_connectors/connectors/postgres/Setup_guide.md
db_connections/scr/all_db_connectors/connectors/postgres/__init__.py
db_connections/scr/all_db_connectors/connectors/postgres/config.py
db_connections/scr/all_db_connectors/connectors/postgres/exceptions.py
db_connections/scr/all_db_connectors/connectors/postgres/health.py
db_connections-1.0.3.dist-info/METADATA
db_connections-1.0.3.dist-info/WHEEL
db_connections-1.0.3.dist-info/RECORD
