Metadata-Version: 2.4
Name: db_connections
Version: 1.0.3
Summary: A unified Python library for managing database connections across multiple Database Management Systems (DBMSs)
Project-URL: Homepage, https://github.com/hosseini72/dbs_connections
Project-URL: Documentation, https://github.com/hosseini72/dbs_connections#readme
Project-URL: Repository, https://github.com/hosseini72/dbs_connections
Project-URL: Issues, https://github.com/hosseini72/dbs_connections/issues
Author-email: Seyyed Mahmoud Hosseini <hosseini72@gmail.com>
License: MIT
Keywords: async,clickhouse,connection,connection-pool,database,health-check,metrics,mongodb,neo4j,nosql,postgres,postgresql,rabbitmq,redis,sql,sync
Classifier: Development Status :: 4 - Beta
Classifier: Intended Audience :: Developers
Classifier: License :: OSI Approved :: MIT License
Classifier: Operating System :: OS Independent
Classifier: Programming Language :: Python :: 3
Classifier: Programming Language :: Python :: 3.8
Classifier: Programming Language :: Python :: 3.9
Classifier: Programming Language :: Python :: 3.10
Classifier: Programming Language :: Python :: 3.11
Classifier: Programming Language :: Python :: 3.12
Classifier: Topic :: Database
Classifier: Topic :: Software Development :: Libraries :: Python Modules
Requires-Python: >=3.8
Provides-Extra: all
Requires-Dist: aio-pika>=9.0.0; extra == 'all'
Requires-Dist: asyncpg>=0.29.0; extra == 'all'
Requires-Dist: clickhouse-connect>=0.6.0; extra == 'all'
Requires-Dist: motor>=3.3.0; extra == 'all'
Requires-Dist: neo4j>=5.0.0; extra == 'all'
Requires-Dist: pika>=1.3.0; extra == 'all'
Requires-Dist: psycopg2-binary>=2.9.9; extra == 'all'
Requires-Dist: pymongo>=4.6.0; extra == 'all'
Requires-Dist: redis[hiredis]>=5.0.0; extra == 'all'
Provides-Extra: clickhouse
Requires-Dist: clickhouse-connect>=0.6.0; extra == 'clickhouse'
Provides-Extra: clickhouse-async
Requires-Dist: clickhouse-connect>=0.6.0; extra == 'clickhouse-async'
Provides-Extra: clickhouse-sync
Requires-Dist: clickhouse-connect>=0.6.0; extra == 'clickhouse-sync'
Provides-Extra: dev
Requires-Dist: black>=23.0.0; extra == 'dev'
Requires-Dist: mypy>=1.0.0; extra == 'dev'
Requires-Dist: pytest-asyncio>=0.21.0; extra == 'dev'
Requires-Dist: pytest-cov>=4.1.0; extra == 'dev'
Requires-Dist: pytest-mock>=3.11.0; extra == 'dev'
Requires-Dist: pytest>=7.4.0; extra == 'dev'
Requires-Dist: ruff>=0.1.0; extra == 'dev'
Provides-Extra: mongodb
Requires-Dist: motor>=3.3.0; extra == 'mongodb'
Requires-Dist: pymongo>=4.6.0; extra == 'mongodb'
Provides-Extra: mongodb-async
Requires-Dist: motor>=3.3.0; extra == 'mongodb-async'
Provides-Extra: mongodb-sync
Requires-Dist: pymongo>=4.6.0; extra == 'mongodb-sync'
Provides-Extra: neo4j
Requires-Dist: neo4j>=5.0.0; extra == 'neo4j'
Provides-Extra: neo4j-async
Requires-Dist: neo4j>=5.0.0; extra == 'neo4j-async'
Provides-Extra: neo4j-sync
Requires-Dist: neo4j>=5.0.0; extra == 'neo4j-sync'
Provides-Extra: postgres
Requires-Dist: asyncpg>=0.29.0; extra == 'postgres'
Requires-Dist: psycopg2-binary>=2.9.9; extra == 'postgres'
Provides-Extra: postgres-async
Requires-Dist: asyncpg>=0.29.0; extra == 'postgres-async'
Provides-Extra: postgres-sync
Requires-Dist: psycopg2-binary>=2.9.9; extra == 'postgres-sync'
Provides-Extra: rabbitmq
Requires-Dist: aio-pika>=9.0.0; extra == 'rabbitmq'
Requires-Dist: pika>=1.3.0; extra == 'rabbitmq'
Provides-Extra: rabbitmq-async
Requires-Dist: aio-pika>=9.0.0; extra == 'rabbitmq-async'
Provides-Extra: rabbitmq-sync
Requires-Dist: pika>=1.3.0; extra == 'rabbitmq-sync'
Provides-Extra: redis
Requires-Dist: redis[hiredis]>=5.0.0; extra == 'redis'
Provides-Extra: redis-async
Requires-Dist: redis[hiredis]>=5.0.0; extra == 'redis-async'
Provides-Extra: redis-sync
Requires-Dist: redis>=5.0.0; extra == 'redis-sync'
Provides-Extra: test
